<?xml version="1.0" encoding="utf-8"?>
<ArrayOfNameList xmlns:xsi="http://www.w3.org/2001/XMLSchema-instance" xmlns:xsd="http://www.w3.org/2001/XMLSchema">
  <NameList>
    <Id>ui_pla2</Id>
    <Name>UI - Plantoid 2</Name>
    <Ships>
      <Generic>
        <NameGroup>
          <Values>
            <string>Acarială</string>
            <string>Acarin</string>
            <string>Acarină</string>
            <string>Albilică</string>
            <string>Albin</string>
            <string>Albinăriță</string>
            <string>Aligaie</string>
            <string>Aligan</string>
            <string>Anacondor</string>
            <string>Anghil</string>
            <string>Anghiță</string>
            <string>Anghiucă</string>
            <string>Anghiunghil</string>
            <string>Anghiunghilă</string>
            <string>Anghiunghiță</string>
            <string>Anghiunghiucă</string>
            <string>Antilopătar</string>
            <string>Arice</string>
            <string>Aricel</string>
            <string>Bacal</string>
            <string>Bacalionim</string>
            <string>Balină</string>
            <string>Baracal</string>
            <string>Baracaliar</string>
            <string>Baracalionim</string>
            <string>Bibiliță</string>
            <string>Brumăriuță</string>
            <string>Cabalistă</string>
            <string>Caliar</string>
            <string>Călugă</string>
            <string>Cambuzie</string>
            <string>Cânepard</string>
            <string>Cânepardal</string>
            <string>Cânepardos</string>
            <string>Cangutan</string>
            <string>Capîntor</string>
            <string>Capîntors</string>
            <string>Capîntorturicată</string>
            <string>Capîntorturicel</string>
            <string>Capîntorturici</string>
            <string>Capîntorturiea</string>
            <string>Capîntorturion</string>
            <string>Căprioarcă</string>
            <string>Carab</string>
            <string>Cărăbătură</string>
            <string>Caracaliar</string>
            <string>Caracalionim</string>
            <string>Cârcă</string>
            <string>Cârsteluță</string>
            <string>Chin</string>
            <string>Chinghil</string>
            <string>Chinghilă</string>
            <string>Chinghiucă</string>
            <string>Chinghiunghiță</string>
            <string>Chițorgan</string>
            <string>Cicoarece</string>
            <string>Cinte</string>
            <string>Cioarcă</string>
            <string>Cioc</string>
            <string>Ciocănitoarece</string>
            <string>Ciocănitorinc</string>
            <string>Ciocănitorinte</string>
            <string>Ciocănitorintez</string>
            <string>Ciocănitorinteză</string>
            <string>Ciocănitorlan</string>
            <string>Ciocârliță</string>
            <string>Ciocîntor</string>
            <string>Ciocîntortură</string>
            <string>Ciocîntorturică</string>
            <string>Ciocîntorturicat</string>
            <string>Ciocîntorturicel</string>
            <string>Ciocîntorturiea</string>
            <string>Ciocîntorturion</string>
            <string>Cleandră</string>
            <string>Cleandril</string>
            <string>Cleandru</string>
            <string>Coadărăbuș</string>
            <string>Condă</string>
            <string>Corosbinărel</string>
            <string>Corosbinăriță</string>
            <string>Crestea</string>
            <string>Crestraș</string>
            <string>Cristeluță</string>
            <string>Cuculbin</string>
            <string>Cuculbină</string>
            <string>Cuculbinar</string>
            <string>Cuculbinărel</string>
            <string>Cuculbinăriță</string>
            <string>Cuculbinel</string>
            <string>Cufundaș</string>
            <string>Culbău</string>
            <string>Culbină</string>
            <string>Culbinar</string>
            <string>Culbinărel</string>
            <string>Culbinel</string>
            <string>Culice</string>
            <string>Culiță</string>
            <string>Curcaci</string>
            <string>Dulgherlan</string>
            <string>Dumbraș</string>
            <string>Ferestea</string>
            <string>Feresteț</string>
            <string>Florinc</string>
            <string>Florintez</string>
            <string>Florinteză</string>
            <string>Florintezoi</string>
            <string>Floris</string>
            <string>Fluturel</string>
            <string>Fundar</string>
            <string>Fundaș</string>
            <string>Furniche</string>
            <string>Furtură</string>
            <string>Furturică</string>
            <string>Furturicat</string>
            <string>Furturice</string>
            <string>Furturiceală</string>
            <string>Furturiea</string>
            <string>Furturion</string>
            <string>Gambulă</string>
            <string>Gârlie</string>
            <string>Ghepar</string>
            <string>Ghepardal</string>
            <string>Ghepardos</string>
            <string>Gher</string>
            <string>Ghiucă</string>
            <string>Ghiunghil</string>
            <string>Ghiunghilă</string>
            <string>Ghiunghiță</string>
            <string>Ghiunghiunghil</string>
            <string>Ghiunghiunghilă</string>
            <string>Ghiunghiunghiță</string>
            <string>Ghiunghiunghiucă</string>
            <string>Gligaie</string>
            <string>Gligator</string>
            <string>Gorie</string>
            <string>Grangutan</string>
            <string>Grindereu</string>
            <string>Gugușter</string>
            <string>Guguștiucă</string>
            <string>Guștiuc</string>
            <string>Guștiucă</string>
            <string>Hermită</string>
            <string>Hipoponei</string>
            <string>Hipoponeț</string>
            <string>Inărel</string>
            <string>Langutan</string>
            <string>Lăstuică</string>
            <string>Leopardal</string>
            <string>Leopardos</string>
            <string>Licurică</string>
            <string>Licuricat</string>
            <string>Licuricată</string>
            <string>Licurice</string>
            <string>Licuriceală</string>
            <string>Licuricel</string>
            <string>Lipitoarece</string>
            <string>Lipiton</string>
            <string>Lopă</string>
            <string>Lorinc</string>
            <string>Lorinte</string>
            <string>Lorintez</string>
            <string>Lorinteză</string>
            <string>Lorintezoi</string>
            <string>Lostrigă</string>
            <string>Luciu</string>
            <string>Măcălean</string>
            <string>Măcăleandră</string>
            <string>Măcăleandril</string>
            <string>Mandră</string>
            <string>Mandru</string>
            <string>Marian</string>
            <string>Marid</string>
            <string>Marin</string>
            <string>Marină</string>
            <string>Măriță</string>
            <string>Merluci</string>
            <string>Mițoran</string>
            <string>Mitorinc</string>
            <string>Mitorinte</string>
            <string>Mitorintez</string>
            <string>Mitorinteză</string>
            <string>Mitorintezoi</string>
            <string>Moacăț</string>
            <string>Mrean</string>
            <string>Muscarab</string>
            <string>Muscaracal</string>
            <string>Muscaracalionim</string>
            <string>Muscaracudă</string>
            <string>Muscaragață</string>
            <string>Muscaras</string>
            <string>Musculic</string>
            <string>Musculice</string>
            <string>Năpârcaci</string>
            <string>Năpârcăiac</string>
            <string>Nevăstun</string>
            <string>Nevesteț</string>
            <string>Nisetruș</string>
            <string>Ornitoare</string>
            <string>Ornitoarece</string>
            <string>Ornitorintez</string>
            <string>Ornitorintezoi</string>
            <string>Ornitorlan</string>
            <string>Pălămâzdră</string>
            <string>Pard</string>
            <string>Păstrunghil</string>
            <string>Păstrunghilă</string>
            <string>Păstrunghiță</string>
            <string>Păstrunghiucă</string>
            <string>Păstruț</string>
            <string>Peliță</string>
            <string>Percarială</string>
            <string>Percarian</string>
            <string>Percarin</string>
            <string>Pescarab</string>
            <string>Pescaracal</string>
            <string>Pescaracudă</string>
            <string>Pescaragață</string>
            <string>Pescaras</string>
            <string>Pietru</string>
            <string>Pițicată</string>
            <string>Pitoare</string>
            <string>Pitoarece</string>
            <string>Pitulic</string>
            <string>Piturnicar</string>
            <string>Poneț</string>
            <string>Poponei</string>
            <string>Popotam</string>
            <string>Porumbie</string>
            <string>Potârnică</string>
            <string>Potârnicar</string>
            <string>Prepelican</string>
            <string>Prigoarece</string>
            <string>Prigoreană</string>
            <string>Prigorilă</string>
            <string>Privighetoarece</string>
            <string>Prundac</string>
            <string>Purică</string>
            <string>Puricat</string>
            <string>Puricată</string>
            <string>Puriceală</string>
            <string>Puricel</string>
            <string>Purici</string>
            <string>Răspariță</string>
            <string>Rățișoare</string>
            <string>Rățișoarece</string>
            <string>Recheat</string>
            <string>Rechelniță</string>
            <string>Rechilă</string>
            <string>Rechinghilă</string>
            <string>Rechinghiță</string>
            <string>Rechinghiunghilă</string>
            <string>Roșioarcă</string>
            <string>Șacaliar</string>
            <string>Șacalionim</string>
            <string>Salamandril</string>
            <string>Salamandru</string>
            <string>Sălămidă</string>
            <string>Scar</string>
            <string>Scaracalionim</string>
            <string>Scaracudă</string>
            <string>Scaras</string>
            <string>Scrumbel</string>
            <string>Sfrânciocârlan</string>
            <string>Sfrânciocârlie</string>
            <string>Sfrânciocârliță</string>
            <string>Sfrânciocîntor</string>
            <string>Sfrânciocîntors</string>
            <string>Smarială</string>
            <string>Smarian</string>
            <string>Smarin</string>
            <string>Smarină</string>
            <string>Șoacă</string>
            <string>Șoară</string>
            <string>Șoare</string>
            <string>Șobol</string>
            <string>Sobolan</string>
            <string>Șorice</string>
            <string>Șoriceală</string>
            <string>Spârcă</string>
            <string>Spârcăiac</string>
            <string>Spurcan</string>
            <string>Stel</string>
            <string>Sticlean</string>
            <string>Sticleandră</string>
            <string>Sticleandril</string>
            <string>Sticleandru</string>
            <string>Știuc</string>
            <string>Striță</string>
            <string>Strugă</string>
            <string>Strunghilă</string>
            <string>Strunghiță</string>
            <string>Strunghiucă</string>
            <string>Strunghiunghil</string>
            <string>Strunghiunghilă</string>
            <string>Strunghiunghiță</string>
            <string>Strunghiunghiucă</string>
            <string>Sturică</string>
            <string>Sturicat</string>
            <string>Sturicată</string>
            <string>Sturice</string>
            <string>Sturiceală</string>
            <string>Sturicel</string>
            <string>Sturici</string>
            <string>Sturiea</string>
            <string>Surică</string>
            <string>Suricat</string>
            <string>Surice</string>
            <string>Suriceală</string>
            <string>Suricel</string>
            <string>Surici</string>
            <string>Surligaie</string>
            <string>Surligan</string>
            <string>Șurligan</string>
            <string>Surligator</string>
            <string>Șurligator</string>
            <string>Tamarială</string>
            <string>Tamarian</string>
            <string>Tamarid</string>
            <string>Tamarină</string>
            <string>Taran</string>
            <string>Termină</string>
            <string>Țicleandră</string>
            <string>Țicleandril</string>
            <string>Țicleandru</string>
            <string>Tintiță</string>
            <string>Țintiță</string>
            <string>Țipariță</string>
            <string>Tiuc</string>
            <string>Trântors</string>
            <string>Trântortură</string>
            <string>Trântorturică</string>
            <string>Trântorturicat</string>
            <string>Trântorturiceală</string>
            <string>Trântorturiea</string>
            <string>Trântorturion</string>
            <string>Turtunar</string>
            <string>Turtură</string>
            <string>Turturicat</string>
            <string>Turturicată</string>
            <string>Turturiceală</string>
            <string>Turturicel</string>
            <string>Turturici</string>
            <string>Turturion</string>
            <string>Uligaie</string>
            <string>Uligator</string>
            <string>Urangur</string>
            <string>Urechin</string>
            <string>Urechinghil</string>
            <string>Urechinghilă</string>
            <string>Urechinghiță</string>
            <string>Urechinghiucă</string>
            <string>Vânture</string>
            <string>Varancă</string>
            <string>Varantulă</string>
            <string>Vindel</string>
            <string>Zglăvoacăț</string>
            <string>Zimbravă</string>
            <string>Zvârlugăriță</string>
          </Values>
        </NameGroup>
      </Generic>
    </Ships>
    <Armies>
      <FleetSequentialName>%O% Spaceleaves</FleetSequentialName>
      <DefenceArmySequentialName>%O% Bark Division</DefenceArmySequentialName>
      <AssaultArmySequentialName>%O% Thorn Regiment</AssaultArmySequentialName>
      <OccupationArmySequentialName>%0% Vine Detachment</OccupationArmySequentialName>
      <SlaveArmySequentialName>%O% Chained Weeds</SlaveArmySequentialName>
      <CloneArmySequentialName>%O% Clone Troopers</CloneArmySequentialName>
      <UndeadArmySequentialName>%O% Withered Battalion</UndeadArmySequentialName>
      <RoboticDefenceArmySequentialName>%O% Steel Bark Division</RoboticDefenceArmySequentialName>
      <RoboticAssaultArmySequentialName>%O% Steel Thorn Regiment</RoboticAssaultArmySequentialName>
      <RoboticOccupationArmySequentialName>%0% Steel Vine Detachment</RoboticOccupationArmySequentialName>
      <AndroidDefenceArmySequentialName>%O% Synthetic Bark Division</AndroidDefenceArmySequentialName>
      <AndroidAssaultArmySequentialName>%O% Synthetic Thorn Regiment</AndroidAssaultArmySequentialName>
      <PsionicArmySequentialName>%O% Psionic Stem Squad</PsionicArmySequentialName>
      <XenomorphArmySequentialName>%O% Mutant Weed Swarm</XenomorphArmySequentialName>
      <SuperSoldierArmySequentialName>%O% Augmented Root Squad</SuperSoldierArmySequentialName>
    </Armies>
    <Planets>
      <Generic>
        <NameGroup>
          <Values>
            <string>Amărășeni</string>
            <string>Ampoia</string>
            <string>Andrei</string>
            <string>Argești</string>
            <string>Armășag</string>
            <string>Aroneasa</string>
            <string>Aurele</string>
            <string>Axinteia</string>
            <string>Băileni</string>
            <string>Bălanița</string>
            <string>Bâltei</string>
            <string>Bălușeri</string>
            <string>Banpotoci</string>
            <string>Bărboaia</string>
            <string>Bărbuleni</string>
            <string>Bârzei</string>
            <string>Baurcina</string>
            <string>Băuța</string>
            <string>Bejani</string>
            <string>Bereva</string>
            <string>Berghiel</string>
            <string>Blăjena</string>
            <string>Bleja</string>
            <string>Blidărei</string>
            <string>Blidia</string>
            <string>Bogeasa</string>
            <string>Bordeana</string>
            <string>Botizantemir</string>
            <string>Brăneasa</string>
            <string>Bratec</string>
            <string>Breznic</string>
            <string>Bucureac</string>
            <string>Bunte</string>
            <string>Buria</string>
            <string>Burilești</string>
            <string>Buruienile</string>
            <string>Calnița</string>
            <string>Câmpie</string>
            <string>Căpușniceni</string>
            <string>Cărămașda</string>
            <string>Caraniș</string>
            <string>Carasta</string>
            <string>Cărbunar</string>
            <string>Carca</string>
            <string>Cârlița</string>
            <string>Cârloi</string>
            <string>Castra</string>
            <string>Catalin</string>
            <string>Catanei</string>
            <string>Cavadia</string>
            <string>Chei</string>
            <string>Cherechi</string>
            <string>Chetroși</string>
            <string>Chiliași</string>
            <string>Chioarei</string>
            <string>Chiojd</string>
            <string>Chișcăuți</string>
            <string>Ciocila</string>
            <string>Ciorteșca</string>
            <string>Cipria</string>
            <string>Cișmeaua</string>
            <string>Cișmeleuș</string>
            <string>Clănicea</string>
            <string>Cleanca</string>
            <string>Clopotivani</string>
            <string>Cochiș</string>
            <string>Cojgăreni</string>
            <string>Colibia</string>
            <string>Colonț</string>
            <string>Corșoreni</string>
            <string>Corugeni</string>
            <string>Costârnic</string>
            <string>Coțofeni</string>
            <string>Covrieșeni</string>
            <string>Crăgușeni</string>
            <string>Creveni</string>
            <string>Cristorești</string>
            <string>Curca</string>
            <string>Danculești</string>
            <string>Dănile</string>
            <string>Darovăț</string>
            <string>Dăscăeți</string>
            <string>Dedovinari</string>
            <string>Derșin</string>
            <string>Dolinți</string>
            <string>Dracșa</string>
            <string>Drenci</string>
            <string>Drete</string>
            <string>Dubăsari</string>
            <string>Făgăra</string>
            <string>Fălciug</string>
            <string>Fetei</string>
            <string>Florile</string>
            <string>Fundenfeld</string>
            <string>Furduc</string>
            <string>Gălăngărești</string>
            <string>Gălățig</string>
            <string>Galbi</string>
            <string>Gâlcea</string>
            <string>Galicioara</string>
            <string>Gârdan</string>
            <string>Generișoara</string>
            <string>Ghindoaia</string>
            <string>Ghinoșica</string>
            <string>Ghiocani</string>
            <string>Ghioroiești</string>
            <string>Ghizeni</string>
            <string>Ginersig</string>
            <string>Glăvicești</string>
            <string>Glodișești</string>
            <string>Gogoșani</string>
            <string>Gohorăniceni</string>
            <string>Gorgoș</string>
            <string>Gorunga</string>
            <string>Gostache</string>
            <string>Gostileasa</string>
            <string>Gratic</string>
            <string>Grivina</string>
            <string>Guraniștari</string>
            <string>Hădăra</string>
            <string>Horodnic</string>
            <string>Iacova</string>
            <string>Iaslova</string>
            <string>Idiceni</string>
            <string>Idicești</string>
            <string>Idici</string>
            <string>Iesler</string>
            <string>Igiroslogea</string>
            <string>Ileanca</string>
            <string>Kogălnița</string>
            <string>Lăschiz</string>
            <string>Lăzăroaia</string>
            <string>Leurdaș</string>
            <string>Lingureni</string>
            <string>Lupărești</string>
            <string>Mădărești</string>
            <string>Magherani</string>
            <string>Măgherechi</string>
            <string>Mănăsoaia</string>
            <string>Mănic</string>
            <string>Margineasca</string>
            <string>Mărginești</string>
            <string>Mari</string>
            <string>Martinovca</string>
            <string>Medișor</string>
            <string>Merendin</string>
            <string>Miheleșoi</string>
            <string>Mirșida</string>
            <string>Mogoșa</string>
            <string>Motnărești</string>
            <string>Munte</string>
            <string>Munteniș</string>
            <string>Muntești</string>
            <string>Mureșel</string>
            <string>Nandrilaca</string>
            <string>Negriteni</string>
            <string>Negrușani</string>
            <string>Nenci</string>
            <string>Noișteana</string>
            <string>Odorea</string>
            <string>Ormindia</string>
            <string>Oțele</string>
            <string>Panaitoasa</string>
            <string>Panicel</string>
            <string>Pârâieni</string>
            <string>Pârjova</string>
            <string>Pârtești</string>
            <string>Pecichești</string>
            <string>Perișoara</string>
            <string>Pești</string>
            <string>Pietrișor</string>
            <string>Plavăț</string>
            <string>Porta</string>
            <string>Poștei</string>
            <string>Predea</string>
            <string>Prevediaș</string>
            <string>Prigorești</string>
            <string>Prilovca</string>
            <string>Progrești</string>
            <string>Pustorești</string>
            <string>Putnei</string>
            <string>Rânghi</string>
            <string>Râșnovăț</string>
            <string>Remet</string>
            <string>Richioaia</string>
            <string>Rogoanele</string>
            <string>Rostolache</string>
            <string>Săcăreți</string>
            <string>Sacoș</string>
            <string>Săcuieni</string>
            <string>Săgeataluri</string>
            <string>Sălăteni</string>
            <string>Sălișteana</string>
            <string>Sălnicel</string>
            <string>Sângăraș</string>
            <string>Sânlean</string>
            <string>Sânsimioarele</string>
            <string>Sânzi</string>
            <string>Scoara</string>
            <string>Sfoartaul</string>
            <string>Siliștei</string>
            <string>Șiștat</string>
            <string>Smadovei</string>
            <string>Somești</string>
            <string>Șoptelnic</string>
            <string>Stăuceava</string>
            <string>Ștefan</string>
            <string>Sucuteni</string>
            <string>Șuletari</string>
            <string>Târâta</string>
            <string>Tărcașa</string>
            <string>Târg</string>
            <string>Țelin</string>
            <string>Ticvani</string>
            <string>Ţigănești</string>
            <string>Țigăneşti</string>
            <string>Tighiș</string>
            <string>Tirea</string>
            <string>Tomnatici</string>
            <string>Topleni</string>
            <string>Trohanisfeldea</string>
            <string>Trusctieni</string>
            <string>Tudorea</string>
            <string>Tulghez</string>
            <string>Ungurile</string>
            <string>Vârghinderfeld</string>
            <string>Verendeni</string>
            <string>Verneți</string>
            <string>Volovata</string>
            <string>Zahoreluci</string>
            <string>Zerveni</string>
            <string>Zgripceștiug</string>
            <string>Zoloteasca</string>
            <string>Zvorăniceni</string>
          </Values>
        </NameGroup>
      </Generic>
    </Planets>
    <Characters>
      <CharacterNames>
        <Id>default</Id>
        <Weight>100</Weight>
        <FullNames>
          <NameGroup>
            <Values>
              <string>Abană</string>
              <string>Acantalup</string>
              <string>Agurice</string>
              <string>Aguricea</string>
              <string>Albă</string>
              <string>Albăstrag</string>
              <string>Amărălabă</string>
              <string>Amărea</string>
              <string>Ambrozinchin</string>
              <string>Ananason</string>
              <string>Anas</string>
              <string>Anasie</string>
              <string>Angea</string>
              <string>Anghel</string>
              <string>Arindecea</string>
              <string>Arnic</string>
              <string>Arniță</string>
              <string>Arșinicior</string>
              <string>Asparanason</string>
              <string>Asparasol</string>
              <string>Asparasole</string>
              <string>Bălbină</string>
              <string>Bălbior</string>
              <string>Banană</string>
              <string>Bananie</string>
              <string>Barabă</string>
              <string>Betulacă</string>
              <string>Bighirea</string>
              <string>Boborniță</string>
              <string>Boglariță</string>
              <string>Broasă</string>
              <string>Brumăreală</string>
              <string>Brumăriță</string>
              <string>Brustan</string>
              <string>Brusturoi</string>
              <string>Bumbă</string>
              <string>Caisinel</string>
              <string>Călambă</string>
              <string>Calarabulă</string>
              <string>Camelinuță</string>
              <string>Cânepă</string>
              <string>Cantă</string>
              <string>Cărăluță</string>
              <string>Caramză</string>
              <string>Cârciog</string>
              <string>Cârciognă</string>
              <string>Cenușă</string>
              <string>Cenușărea</string>
              <string>Cercelușă</string>
              <string>Chiparoască</string>
              <string>Chiparos</string>
              <string>Chiperuță</string>
              <string>Cicoasă</string>
              <string>Cicoasă</string>
              <string>Citrice</string>
              <string>Ciuciulin</string>
              <string>Ciuciulină</string>
              <string>Ciulete</string>
              <string>Ciuli</string>
              <string>Ciumăreală</string>
              <string>Ciumărie</string>
              <string>Ciumăriță</string>
              <string>Clementiță</string>
              <string>Clocoșel</string>
              <string>Clocoșică</string>
              <string>Clocoțea</string>
              <string>Clopoțele</string>
              <string>Clopoțeler</string>
              <string>Coacă</string>
              <string>Coacăză</string>
              <string>Cocârțâitoare</string>
              <string>Cocoare</string>
              <string>Coconariță</string>
              <string>Cocotici</string>
              <string>Condurariță</string>
              <string>Corcov</string>
              <string>Coriță</string>
              <string>Cornacadea</string>
              <string>Coronică</string>
              <string>Cortinariță</string>
              <string>Creasă</string>
              <string>Crestic</string>
              <string>Crestriță</string>
              <string>Crețișor</string>
              <string>Cristenea</string>
              <string>Cristeneală</string>
              <string>Cristolnic</string>
              <string>Crizanie</string>
              <string>Croambă</string>
              <string>Crușine</string>
              <string>Cucuraș</string>
              <string>Cucuraș</string>
              <string>Cucurbețea</string>
              <string>Cucurbețică</string>
              <string>Cucurel</string>
              <string>Cucuruz</string>
              <string>Cucuta</string>
              <string>Cuișor</string>
              <string>Curechiușă</string>
              <string>Degetarină</string>
              <string>Degetăruță</string>
              <string>Dentină</string>
              <string>Dorniță</string>
              <string>Dosnic</string>
              <string>Drăcină</string>
              <string>Drăciuniță</string>
              <string>Dragoră</string>
              <string>Drobușoară</string>
              <string>Dumbel</string>
              <string>Dumbravniță</string>
              <string>Dumitrică</string>
              <string>Dungă</string>
              <string>Fasol</string>
              <string>Fecioasă</string>
              <string>Ferigar</string>
              <string>Firici</string>
              <string>Fistică</string>
              <string>Flămânărică</string>
              <string>Flocotici</string>
              <string>Flocotiș</string>
              <string>Frăgulă</string>
              <string>Frăguliță</string>
              <string>Frăsinei</string>
              <string>Frigaretă</string>
              <string>Friguță</string>
              <string>Fuliță</string>
              <string>Găinușăreasă</string>
              <string>Gălbenea</string>
              <string>Gălbeneală</string>
              <string>Gălbenele</string>
              <string>Gălbenușărea</string>
              <string>Gălbior</string>
              <string>Gălbisă</string>
              <string>Gambilă</string>
              <string>Gardei</string>
              <string>Gârniță</string>
              <string>Gemănarie</string>
              <string>Ghină</string>
              <string>Ghinariță</string>
              <string>Gladiolă</string>
              <string>Guliță</string>
              <string>Harbust</string>
              <string>Himan</string>
              <string>Hrici</string>
              <string>Iberică</string>
              <string>Imortensie</string>
              <string>Împărătăciune</string>
              <string>Indru</string>
              <string>Îngerină</string>
              <string>Ipcăriță</string>
              <string>Iperigă</string>
              <string>Jneapă</string>
              <string>Lămâioară</string>
              <string>Lămâiță</string>
              <string>Lămânărică</string>
              <string>Laricea</string>
              <string>Lăsnic</string>
              <string>Lăsnică</string>
              <string>Lavrentiță</string>
              <string>Limbar</string>
              <string>Linguraș</string>
              <string>Lumânăriță</string>
              <string>Luminecea</string>
              <string>Luntrică</string>
              <string>Luntrice</string>
              <string>Luntrilis</string>
              <string>Măceș</string>
              <string>Măcieșă</string>
              <string>Măcrimioară</string>
              <string>Măcrimioară</string>
              <string>Măcrișor</string>
              <string>Maghiroancă</string>
              <string>Măghiroancă</string>
              <string>Măluricică</string>
              <string>Mânărea</string>
              <string>Mandafir</string>
              <string>Mandragoste</string>
              <string>Mătăcină</string>
              <string>Mătrăgulă</string>
              <string>Mătrăguță</string>
              <string>Mătrea</string>
              <string>Matrunjel</string>
              <string>Măzărică</string>
              <string>Micsandru</string>
              <string>Mireastă</string>
              <string>Mitrice</string>
              <string>Morcoduș</string>
              <string>Morcodușă</string>
              <string>Mutulipan</string>
              <string>Năsturoi</string>
              <string>Năsturoiaș</string>
              <string>Nectariță</string>
              <string>Nemțișoară</string>
              <string>Nemțișoare</string>
              <string>Nemțișoriță</string>
              <string>Nitar</string>
              <string>Obligea</string>
              <string>Ochișoriță</string>
              <string>Odoleandru</string>
              <string>Oleandră</string>
              <string>Opunțică</string>
              <string>Paciulin</string>
              <string>Păduchet</string>
              <string>Pangelică</string>
              <string>Pangelinuță</string>
              <string>Pangerină</string>
              <string>Pansea</string>
              <string>Pansevie</string>
              <string>Paragus</string>
              <string>Paranason</string>
              <string>Paranghel</string>
              <string>Păstârnacadea</string>
              <string>Păstârnătoare</string>
              <string>Păstrice</string>
              <string>Pătlăgeată</string>
              <string>Pelină</string>
              <string>Pidosnicior</string>
              <string>Pietricel</string>
              <string>Pintenași</string>
              <string>Pipere</string>
              <string>Pitărel</string>
              <string>Pitoare</string>
              <string>Plăcină</string>
              <string>Plăcioasă</string>
              <string>Plămâie</string>
              <string>Plămânăreală</string>
              <string>Plămânăriță</string>
              <string>Plămânzică</string>
              <string>Plescanția</string>
              <string>Pojarnic</string>
              <string>Poroambă</string>
              <string>Poroancă</string>
              <string>Poroasă</string>
              <string>Poroască</string>
              <string>Porumbă</string>
              <string>Porumbac</string>
              <string>Porumbeț</string>
              <string>Prestie</string>
              <string>Pufulie</string>
              <string>Puricică</string>
              <string>Rabarbă</string>
              <string>Răchie</string>
              <string>Rădăcintă</string>
              <string>Răzăchitan</string>
              <string>Rechi</string>
              <string>Ridichioară</string>
              <string>Robiniță</string>
              <string>Rocoțel</string>
              <string>Roinic</string>
              <string>Romanic</string>
              <string>Roscot</string>
              <string>Rostogol</string>
              <string>Rotoțel</string>
              <string>Rotunjoaică</string>
              <string>Rubarbăr</string>
              <string>Rumeneasă</string>
              <string>Rușin</string>
              <string>Rușuliție</string>
              <string>Safteregoaie</string>
              <string>Săgea</string>
              <string>Samurariță</string>
              <string>Sansea</string>
              <string>Săpunele</string>
              <string>Saschiușă</string>
              <string>Schin</string>
              <string>Schină</string>
              <string>Schiu</string>
              <string>Schiușă</string>
              <string>Scobiceaf</string>
              <string>Scoroaică</string>
              <string>Secăreală</string>
              <string>Șerlaiță</string>
              <string>Șiarchină</string>
              <string>Șiarchinel</string>
              <string>Sinceriu</string>
              <string>Sisină</string>
              <string>Smochinel</string>
              <string>Smochiță</string>
              <string>Somnișoară</string>
              <string>Somnoroaică</string>
              <string>Somnoroancă</string>
              <string>Șopârlai</string>
              <string>Sparagus</string>
              <string>Sparasol</string>
              <string>Sparasole</string>
              <string>Sperigel</string>
              <string>Stânjen</string>
              <string>Steliție</string>
              <string>Sterea</string>
              <string>Ștevieria</string>
              <string>Stru</string>
              <string>Strugurea</string>
              <string>Stupin</string>
              <string>Suliță</string>
              <string>Tabanos</string>
              <string>Tămâi</string>
              <string>Tătănea</string>
              <string>Tătănească</string>
              <string>Tătarniță</string>
              <string>Teișoriță</string>
              <string>Țelin</string>
              <string>Țelinuță</string>
              <string>Tinghină</string>
              <string>Tradescai</string>
              <string>Tradescaiță</string>
              <string>Trăguliție</string>
              <string>Trăgună</string>
              <string>Trandarin</string>
              <string>Trandarină</string>
              <string>Tremuriceaf</string>
              <string>Trifoi</string>
              <string>Troscuță</string>
              <string>Tufănea</string>
              <string>Tufăneasă</string>
              <string>Tulică</string>
              <string>Turicariță</string>
              <string>Turicică</string>
              <string>Unguricea</string>
              <string>Unguricică</string>
              <string>Ungurijoare</string>
              <string>Urechi</string>
              <string>Urechi</string>
              <string>Urechie</string>
              <string>Urechiușă</string>
              <string>Usture</string>
              <string>Usturel</string>
              <string>Usturoasă</string>
              <string>Usturoasă</string>
              <string>Usturoască</string>
              <string>Usturoiță</string>
              <string>Valerian</string>
              <string>Vânătarnic</string>
              <string>Velniță</string>
              <string>Veninare</string>
              <string>Verige</string>
              <string>Vetrică</string>
              <string>Vineț</string>
              <string>Vinețea</string>
              <string>Vitrică</string>
              <string>Vitrigoaie</string>
              <string>Vitriță</string>
              <string>Voiniță</string>
              <string>Vulturicariță</string>
              <string>Vulturiță</string>
              <string>Zambir</string>
              <string>Zarnac</string>
              <string>Zarză</string>
              <string>Zbârciumăfaie</string>
              <string>Zbârciumăreală</string>
              <string>Zbură</string>
              <string>Zizanier</string>
            </Values>
          </NameGroup>
        </FullNames>
      </CharacterNames>
    </Characters>
  </NameList>
</ArrayOfNameList>