<?xml version="1.0" encoding="utf-8"?>
<ArrayOfNameList xmlns:xsi="http://www.w3.org/2001/XMLSchema-instance" xmlns:xsd="http://www.w3.org/2001/XMLSchema">
  <NameList>
    <Id>civbe_human_irish</Id>
    <Name>Civilization: Beyond Earth - Human - Irish</Name>
    <Places>
      <Cities>
        <NameGroup>
          <Name>Cities - Civilization: Beyond Earth</Name> <!-- North Sea Alliance -->
          <Values>
            <string>Eilemuir</string>
          </Values>
        </NameGroup>
      </Cities>
    </Places>
    <Planets>
      <Generic>
        <NameGroup>
          <Name>Cities - Civilization: Beyond Earth</Name> <!-- North Sea Alliance -->
          <Values>
            <string>Eilemuir</string>
          </Values>
        </NameGroup>
      </Generic>
    </Planets>
  </NameList>
</ArrayOfNameList>