<?xml version="1.0" encoding="utf-8"?>
<ArrayOfNameList xmlns:xsi="http://www.w3.org/2001/XMLSchema-instance" xmlns:xsd="http://www.w3.org/2001/XMLSchema">
  <NameList>
    <Id>marvel_human_african</Id>
    <Name>Marvel - Human - African</Name>
    <Denonyms>
      <NameGroup>
        <Name>Denonyms - Marvel</Name>
        <Values>
          <string>Wakandan</string>
        </Values>
      </NameGroup>
    </Denonyms>
    <Places>
      <Countries>
        <NameGroup>
          <Name>Countries - Marvel</Name>
          <Values>
            <string>Wakanda</string>
          </Values>
        </NameGroup>
      </Countries>
      <Mountains>
        <NameGroup>
          <Name>Mountains - Marvel</Name>
          <Values>
            <string>Bashenga</string>
          </Values>
        </NameGroup>
      </Mountains>
    </Places>
    <GreatPeople>
      <LeadersTier1>
        <NameGroup>
          <Name>Leaders</Name>
          <Values>
            <string>Bashenga</string>
          </Values>
        </NameGroup>
      </LeadersTier1>
    </GreatPeople>
    <Planets>
      <Generic>
        <NameGroup>
          <Name>Countries - Marvel</Name>
          <Values>
            <string>Wakanda</string>
          </Values>
        </NameGroup>
      </Generic>
    </Planets>
  </NameList>
</ArrayOfNameList>