<?xml version="1.0" encoding="utf-8"?>
<ArrayOfNameList xmlns:xsi="http://www.w3.org/2001/XMLSchema-instance" xmlns:xsd="http://www.w3.org/2001/XMLSchema">
  <NameList>
    <Id>human_spanish</Id>
    <Name>Human - Spanish</Name>
    <Denonyms>
      <NameGroup>
        <Name>Denonyms</Name>
        <Values>
          <string>Argentinian</string>
        </Values>
      </NameGroup>
    </Denonyms>
    <Places>
      <Countries>
        <NameGroup>
          <Name>Countries</Name>
          <Values>
            <string>Argentina</string>
          </Values>
        </NameGroup>
      </Countries>
      <Cities>
        <NameGroup>
          <Name>Cities</Name>
          <Values>
            <string>Buenos Aires</string>
          </Values>
        </NameGroup>
      </Cities>
      <Mountains>
        <NameGroup>
          <Name>Mountains</Name>
          <Values>
            <string>Andes</string>
          </Values>
        </NameGroup>
      </Mountains>
      <Deserts>
        <NameGroup>
          <Name>Deserts</Name>
          <Values>
            <string>Patagonia</string>
          </Values>
        </NameGroup>
      </Deserts>
    </Places>
    <Companies>
      <SpacecraftManufacturers>
        <NameGroup>
          <Name>Spacecraft manufacturers</Name>
          <Values>
            <string>INVAP</string>
          </Values>
        </NameGroup>
      </SpacecraftManufacturers>
    </Companies>
    <Warfare>
      <BattleLocations>
        <NameGroup>
          <Name>Battle locations</Name>
          <Values>
            <string>Goose Green</string>
          </Values>
        </NameGroup>
      </BattleLocations>
    </Warfare>
  </NameList>
</ArrayOfNameList>