<?xml version="1.0" encoding="utf-8"?>
<ArrayOfNameList xmlns:xsi="http://www.w3.org/2001/XMLSchema-instance" xmlns:xsd="http://www.w3.org/2001/XMLSchema">
  <NameList>
    <Id>human_celtic</Id>
    <Name>Human - Celtic</Name>
    <Denonyms>
      <NameGroup>
        <Name>Denonyms</Name>
        <Values>
            <string>Breton</string>
            <string>Celtic</string>
            <string>Irish</string>
            <string>Scottish</string>
            <string>Welsh</string>
        </Values>
      </NameGroup>
    </Denonyms>
    <Places>
      <Countries>
        <NameGroup>
          <Name>Countries</Name>
          <Values>
            <string>Britanny</string>
            <string>Ireland</string>
            <string>Scotland</string>
            <string>Wales</string>
          </Values>
        </NameGroup>
      </Countries>
      <Cities>
        <NameGroup>
          <Name>Cities - Ireland - English names</Name>
          <Values>
            <string>Belfast</string>
            <string>Cork</string>
            <string>Dublin</string>
          </Values>
        </NameGroup>
        <NameGroup>
          <Name>Cities - Ireland - Irish names</Name>
          <Values>
            <string>Corcaigh</string>
          </Values>
        </NameGroup>
        <NameGroup>
          <Name>Cities - Scotland</Name>
          <Values>
            <string>Aberdeen</string>
            <string>Edinburgh</string>
            <string>Glasgow</string>
          </Values>
        </NameGroup>
        <NameGroup>
          <Name>Cities - Wales</Name>
          <Values>
            <string>Cardiff</string>
            <string>Swansea</string>
          </Values>
        </NameGroup>
      </Cities>
      <Lakes>
        <NameGroup>
          <Name>Lakes - Scotland</Name>
          <Values>
            <string>Loch Ness</string>
          </Values>
        </NameGroup>
      </Lakes>
    </Places>
    <Warfare>
      <Weapons>
        <NameGroup>
          <Name></Name>
          <Values>
          </Values>
        </NameGroup>
      </Weapons>
      <MilitaryUnitTypes>
        <NameGroup>
          <Name>Military Unit Types - Scottish</Name>
          <Values>
            <string>Highlander</string>
          </Values>
        </NameGroup>
      </MilitaryUnitTypes>
    </Warfare>
    <MythologicalCreatures>
      <NameGroup>
        <Name>Mythological Creatures - Cornish</Name>
        <Values>
          <string>Spriggan</string>
        </Values>
      </NameGroup>
      <NameGroup>
        <Name>Mythological Creatures - Irish</Name>
        <Values>
          <string>Banshee</string>
        </Values>
      </NameGroup>
    </MythologicalCreatures>
    <Ships>
      <Generic />
      <Corvette>
        <NameGroup>
          <Name>Persons - Leaders</Name>
          <Values>
            <string>Gwendolen</string>
          </Values>
        </NameGroup>
        <NameGroup>
          <Name>Persons - Leaders - Welsh</Name>
          <Values>
            <string>Gwenllian</string>
          </Values>
        </NameGroup>
        <NameGroup>
          <Name>Mythology</Name>
          <Values>
            <string>Morrigan</string>
          </Values>
        </NameGroup>
      </Corvette>
      <Destroyer>
        <NameGroup>
          <Name></Name>
          <Values>
          </Values>
        </NameGroup>
      </Destroyer>
      <Cruiser>
        <NameGroup>
          <Name></Name>
          <Values>
          </Values>
        </NameGroup>
      </Cruiser>
      <Battleship>
        <NameGroup>
          <Name></Name>
          <Values>
          </Values>
        </NameGroup>
      </Battleship>
      <Constructor>
        <NameGroup>
          <Name>Persons - Mythology - Irish</Name>
          <Values>
            <string>Creidhne</string>
            <string>Goibniu</string>
            <string>Luchtaine</string>
          </Values>
        </NameGroup>
      </Constructor>
      <Science>
        <NameGroup>
          <Name>Persons - Scientists - Irish</Name>
          <Values>
            <string>Kelvin</string>
          </Values>
        </NameGroup>
      </Science>
      <Coloniser>
        <NameGroup>
          <Name></Name>
          <Values>
          </Values>
        </NameGroup>
      </Coloniser>
    </Ships>
    <ShipClasses>
      <Generic>
        <NameGroup>
          <Name>Aircraft manufacturers - Irish</Name>
          <Values>
            <string>AerCap</string>
          </Values>
        </NameGroup>
      </Generic>
    </ShipClasses>
    <Stations>
        <MilitaryStations>
        <Generic>
            <NameGroup>
                <Name></Name>
                <Values>
                </Values>
            </NameGroup>
        </Generic>
        </MilitaryStations>
    </Stations>
    <Planets>
      <Generic>
        <NameGroup>
          <Name>Civilisation: Beyond Earth - North Sea Alliance - Irish</Name>
          <Values>
            <string>Eilemuir</string>
          </Values>
        </NameGroup>
        <NameGroup>
          <Name>Civilisation: Beyond Earth - North Sea Alliance - Scots Gaelic</Name>
          <Values>
            <string>Bànclagh</string>
            <string>Dunkyle</string>
            <string>Sàmchair</string>
            <string>Sìorraidh</string>
          </Values>
        </NameGroup>
      </Generic>
      <Desert>
        <NameGroup>
          <Name></Name>
          <Values>
          </Values>
        </NameGroup>
      </Desert>
      <Continental>
        <NameGroup>
          <Name></Name>
          <Values>
          </Values>
        </NameGroup>
      </Continental>
      <Ocean>
        <NameGroup>
          <Name>Places</Name>
          <Values>
            <string>Lochness</string>
          </Values>
        </NameGroup>
      </Ocean>
      <Tundra>
        <NameGroup>
          <Name></Name>
          <Values>
          </Values>
        </NameGroup>
      </Tundra>
      <Arctic>
        <NameGroup>
          <Name></Name>
          <Values>
          </Values>
        </NameGroup>
      </Arctic>
      <Tomb>
        <NameGroup>
          <Name></Name>
          <Values>
          </Values>
        </NameGroup>
      </Tomb>
      <Alpine>
        <NameGroup>
          <Name></Name>
          <Values>
          </Values>
        </NameGroup>
      </Alpine>
      <Molten>
        <NameGroup>
          <Name></Name>
          <Values>
          </Values>
        </NameGroup>
      </Molten>
    </Planets>
  </NameList>
</ArrayOfNameList>